{
  "blocks": [
    {
      "id": "executive_summary",
      "kind": "section",
      "sentences": [
        {
          "claimIds": [],
          "id": "sentence-question",
          "kind": "question",
          "locatorIds": [],
          "policyVerdicts": [],
          "snapshotDigests": [],
          "sourceLineageIds": [],
          "text": "Research question: What impacts do data centers have on the communities and environment around them?"
        },
        {
          "claimIds": [
            "claim-electricity-grid-live-belfercenter-org-2943500c8e",
            "claim-electricity-grid-live-stateimpactcenter-org-134751669c"
          ],
          "id": "sentence-electricity-grid",
          "kind": "factual",
          "locatorIds": [
            "span-live-belfercenter-org-2943500c8e",
            "span-live-stateimpactcenter-org-134751669c"
          ],
          "policyVerdicts": [
            "p8.v1-evidence-admission-policy:supported",
            "p8.v1-evidence-admission-policy:supported"
          ],
          "snapshotDigests": [
            "sha256:2943500c8e0fee46ea754631c98dea3766527c53683056131c9328086658ce0c",
            "sha256:134751669c770b96c538e74f95e37c080051edc1a55b7dec8d94bb85c4afd49b"
          ],
          "sourceLineageIds": ["belfercenter-org", "stateimpactcenter-org"],
          "text": "Large data-center loads can strain grid interconnection queues, reliability studies, transmission cost allocation, and generation planning when new campuses concentrate faster than network upgrades."
        },
        {
          "claimIds": [
            "claim-ghg-emissions-live-nih-gov-050055ecca",
            "claim-ghg-emissions-live-msci-com-e9b400d8d6"
          ],
          "id": "sentence-ghg-emissions",
          "kind": "factual",
          "locatorIds": [
            "span-live-nih-gov-050055ecca",
            "span-live-msci-com-e9b400d8d6"
          ],
          "policyVerdicts": [
            "p8.v1-evidence-admission-policy:supported",
            "p8.v1-evidence-admission-policy:supported"
          ],
          "snapshotDigests": [
            "sha256:050055eccad0c493b5560a7a655a418543dcb8c0f98992676c0562b59b04e6f5",
            "sha256:e9b400d8d621e2d9b9e4ee9c0eb4d21bce336e36a8b2c670e04d15c0cb3b7e71"
          ],
          "sourceLineageIds": ["nih-gov", "msci-com"],
          "text": "Data-center climate impact depends on both embodied hardware-and-construction emissions and hourly electricity supply, so annual renewable matching can conflict with hourly fossil generation evidence."
        }
      ],
      "title": "Executive summary"
    },
    {
      "id": "scope_definitions",
      "kind": "section",
      "sentences": [
        {
          "claimIds": [],
          "id": "sentence-scope",
          "kind": "method",
          "locatorIds": [],
          "policyVerdicts": [],
          "snapshotDigests": [],
          "sourceLineageIds": [],
          "text": "The bundle uses P8 report mode, Brave Search discovery, immutable live snapshots, and deterministic report templates."
        }
      ],
      "title": "Scope and definitions"
    },
    {
      "id": "methods_source_criteria",
      "kind": "section",
      "sentences": [
        {
          "claimIds": [],
          "id": "sentence-methods",
          "kind": "method",
          "locatorIds": [],
          "policyVerdicts": [],
          "snapshotDigests": [],
          "sourceLineageIds": [],
          "text": "Search snippets were excluded from evidence; only acquired snapshots with exact locators entered the report manifest."
        }
      ],
      "title": "Methods and source criteria"
    },
    {
      "id": "environmental_effects",
      "kind": "section",
      "sentences": [
        {
          "claimIds": [
            "claim-water-live-eesi-org-bec8ea01d4",
            "claim-water-live-uga-edu-69cc36a64d"
          ],
          "id": "sentence-water",
          "kind": "factual",
          "locatorIds": [
            "span-live-eesi-org-bec8ea01d4",
            "span-live-uga-edu-69cc36a64d"
          ],
          "policyVerdicts": [
            "p8.v1-evidence-admission-policy:supported",
            "p8.v1-evidence-admission-policy:supported"
          ],
          "snapshotDigests": [
            "sha256:bec8ea01d479e9c8b70c3eef63e5df6bc19948bfdaafec809fa9bb7a7f42dac0",
            "sha256:69cc36a64da3b92d9305e1d9321c969053a8e0dcece92dd4d1607f7e10e6926e"
          ],
          "sourceLineageIds": ["eesi-org", "uga-edu"],
          "text": "Water impacts vary sharply by cooling design and drought context: evaporative systems can consume town-scale volumes, while dry or closed-loop alternatives trade lower water use for higher energy demand."
        },
        {
          "claimIds": [
            "claim-land-materials-live-belfercenter-org-2943500c8e",
            "claim-land-materials-live-stateimpactcenter-org-134751669c"
          ],
          "id": "sentence-land-materials",
          "kind": "factual",
          "locatorIds": [
            "span-live-belfercenter-org-2943500c8e",
            "span-live-stateimpactcenter-org-134751669c"
          ],
          "policyVerdicts": [
            "p8.v1-evidence-admission-policy:supported",
            "p8.v1-evidence-admission-policy:supported"
          ],
          "snapshotDigests": [
            "sha256:2943500c8e0fee46ea754631c98dea3766527c53683056131c9328086658ce0c",
            "sha256:134751669c770b96c538e74f95e37c080051edc1a55b7dec8d94bb85c4afd49b"
          ],
          "sourceLineageIds": ["belfercenter-org", "stateimpactcenter-org"],
          "text": "Hyperscale campuses can convert hundreds of acres, disturb habitat, add impervious surface, and create recurring material and e-waste burdens through construction and server-refresh cycles."
        },
        {
          "claimIds": [
            "claim-local-pollution-live-eesi-org-0d574d148f",
            "claim-local-pollution-live-usnews-com-13a2d7bacd"
          ],
          "id": "sentence-local-pollution",
          "kind": "factual",
          "locatorIds": [
            "span-live-eesi-org-0d574d148f",
            "span-live-usnews-com-13a2d7bacd"
          ],
          "policyVerdicts": [
            "p8.v1-evidence-admission-policy:supported",
            "p8.v1-evidence-admission-policy:supported"
          ],
          "snapshotDigests": [
            "sha256:0d574d148f82de5346ecc75bdf0ed2a58db4c9c80a3a3d34143164858e5d1169",
            "sha256:13a2d7bacd07ab1e81821ca3606f8ced8453f4b52b2ecf4ae7a1eda5fb591d3f"
          ],
          "sourceLineageIds": ["eesi-org", "usnews-com"],
          "text": "Local impacts include backup-generator emissions, noise, construction traffic, and visual or operational burdens that may exceed nearby residential limits without enforceable mitigation."
        }
      ],
      "title": "Environmental effects"
    },
    {
      "id": "community_economic_effects",
      "kind": "section",
      "sentences": [
        {
          "claimIds": [
            "claim-housing-services-live-belfercenter-org-2943500c8e",
            "claim-housing-services-live-stateimpactcenter-org-134751669c"
          ],
          "id": "sentence-housing-services",
          "kind": "factual",
          "locatorIds": [
            "span-live-belfercenter-org-2943500c8e",
            "span-live-stateimpactcenter-org-134751669c"
          ],
          "policyVerdicts": [
            "p8.v1-evidence-admission-policy:supported",
            "p8.v1-evidence-admission-policy:supported"
          ],
          "snapshotDigests": [
            "sha256:2943500c8e0fee46ea754631c98dea3766527c53683056131c9328086658ce0c",
            "sha256:134751669c770b96c538e74f95e37c080051edc1a55b7dec8d94bb85c4afd49b"
          ],
          "sourceLineageIds": ["belfercenter-org", "stateimpactcenter-org"],
          "text": "Utility allocation, public-service load, housing pressure, and opportunity costs can shift part of data-center growth costs onto households unless large-load tariffs and local planning controls hold."
        }
      ],
      "title": "Community and economic effects"
    },
    {
      "id": "distributional_environmental_justice",
      "kind": "section",
      "sentences": [
        {
          "claimIds": [
            "claim-environmental-justice-live-belfercenter-org-2943500c8e",
            "claim-environmental-justice-live-stateimpactcenter-org-134751669c"
          ],
          "id": "sentence-environmental-justice",
          "kind": "factual",
          "locatorIds": [
            "span-live-belfercenter-org-2943500c8e",
            "span-live-stateimpactcenter-org-134751669c"
          ],
          "policyVerdicts": [
            "p8.v1-evidence-admission-policy:supported",
            "p8.v1-evidence-admission-policy:supported"
          ],
          "snapshotDigests": [
            "sha256:2943500c8e0fee46ea754631c98dea3766527c53683056131c9328086658ce0c",
            "sha256:134751669c770b96c538e74f95e37c080051edc1a55b7dec8d94bb85c4afd49b"
          ],
          "sourceLineageIds": ["belfercenter-org", "stateimpactcenter-org"],
          "text": "Siting and governance risks are distributional when projects cluster near overburdened tracts or proceed without meaningful consultation with affected local, Indigenous, or environmental-justice communities."
        }
      ],
      "title": "Distributional and environmental-justice analysis"
    },
    {
      "id": "benefits_counterarguments",
      "kind": "section",
      "sentences": [
        {
          "claimIds": [
            "claim-economic-benefits-live-eesi-org-0d574d148f",
            "claim-economic-benefits-live-usnews-com-13a2d7bacd"
          ],
          "id": "sentence-economic-benefits",
          "kind": "factual",
          "locatorIds": [
            "span-live-eesi-org-0d574d148f",
            "span-live-usnews-com-13a2d7bacd"
          ],
          "policyVerdicts": [
            "p8.v1-evidence-admission-policy:supported",
            "p8.v1-evidence-admission-policy:supported"
          ],
          "snapshotDigests": [
            "sha256:0d574d148f82de5346ecc75bdf0ed2a58db4c9c80a3a3d34143164858e5d1169",
            "sha256:13a2d7bacd07ab1e81821ca3606f8ced8453f4b52b2ecf4ae7a1eda5fb591d3f"
          ],
          "sourceLineageIds": ["eesi-org", "usnews-com"],
          "text": "Economic benefits are real but uneven: construction work, permanent jobs, tax revenue, infrastructure investment, abatements, and community-benefit commitments all change the local net effect."
        },
        {
          "claimIds": [
            "claim-ghg-emissions-live-nih-gov-050055ecca",
            "claim-ghg-emissions-live-msci-com-e9b400d8d6"
          ],
          "id": "sentence-contradiction",
          "kind": "uncertainty",
          "locatorIds": [
            "span-live-belfercenter-org-2943500c8e",
            "span-live-stateimpactcenter-org-134751669c"
          ],
          "policyVerdicts": [
            "p8.v1-evidence-admission-policy:supported",
            "p8.v1-evidence-admission-policy:supported"
          ],
          "snapshotDigests": [
            "sha256:2943500c8e0fee46ea754631c98dea3766527c53683056131c9328086658ce0c",
            "sha256:134751669c770b96c538e74f95e37c080051edc1a55b7dec8d94bb85c4afd49b"
          ],
          "sourceLineageIds": ["nih-gov", "msci-com"],
          "text": "Annual matching, hourly load, local grid dispatch, and embodied emissions can point in different directions, so the live report preserves climate-benefit claims as contested where source families diverge."
        }
      ],
      "title": "Benefits and counterarguments"
    },
    {
      "id": "context_comparison",
      "kind": "section",
      "sentences": [
        {
          "claimIds": [
            "claim-variation-live-eesi-org-bec8ea01d4",
            "claim-variation-live-uga-edu-69cc36a64d"
          ],
          "id": "sentence-variation",
          "kind": "factual",
          "locatorIds": [
            "span-live-eesi-org-bec8ea01d4",
            "span-live-uga-edu-69cc36a64d"
          ],
          "policyVerdicts": [
            "p8.v1-evidence-admission-policy:supported",
            "p8.v1-evidence-admission-policy:supported"
          ],
          "snapshotDigests": [
            "sha256:bec8ea01d479e9c8b70c3eef63e5df6bc19948bfdaafec809fa9bb7a7f42dac0",
            "sha256:69cc36a64da3b92d9305e1d9321c969053a8e0dcece92dd4d1607f7e10e6926e"
          ],
          "sourceLineageIds": ["eesi-org", "uga-edu"],
          "text": "No single average data center describes the sector: impacts vary by facility type, climate, grid mix, cooling architecture, scale, lifecycle stage, and operating flexibility."
        }
      ],
      "title": "Context comparison"
    },
    {
      "id": "mitigations_policy_options",
      "kind": "section",
      "sentences": [
        {
          "claimIds": [
            "claim-mitigation-policy-live-belfercenter-org-2943500c8e",
            "claim-mitigation-policy-live-stateimpactcenter-org-134751669c"
          ],
          "id": "sentence-mitigation-policy",
          "kind": "factual",
          "locatorIds": [
            "span-live-belfercenter-org-2943500c8e",
            "span-live-stateimpactcenter-org-134751669c"
          ],
          "policyVerdicts": [
            "p8.v1-evidence-admission-policy:supported",
            "p8.v1-evidence-admission-policy:supported"
          ],
          "snapshotDigests": [
            "sha256:2943500c8e0fee46ea754631c98dea3766527c53683056131c9328086658ce0c",
            "sha256:134751669c770b96c538e74f95e37c080051edc1a55b7dec8d94bb85c4afd49b"
          ],
          "sourceLineageIds": ["belfercenter-org", "stateimpactcenter-org"],
          "text": "Mitigation options include dry or hybrid cooling, hourly clean-energy procurement, demand flexibility, large-load tariff classes, cumulative-impact permitting, and enforceable community-benefit agreements."
        }
      ],
      "title": "Mitigations and policy options"
    },
    {
      "id": "conflicts_uncertainties_gaps",
      "kind": "section",
      "sentences": [
        {
          "claimIds": [],
          "id": "sentence-gap-cycle",
          "kind": "method",
          "locatorIds": [],
          "policyVerdicts": [],
          "snapshotDigests": [],
          "sourceLineageIds": [],
          "text": "The live run performed a second evidence-driven cycle for coverage and dissent checks before publication."
        }
      ],
      "title": "Conflicts, uncertainties, and gaps"
    },
    {
      "id": "conclusion",
      "kind": "section",
      "sentences": [
        {
          "claimIds": [],
          "id": "sentence-conclusion",
          "kind": "method",
          "locatorIds": [],
          "policyVerdicts": [],
          "snapshotDigests": [],
          "sourceLineageIds": [],
          "text": "The report answers from admitted live public-web evidence and records limitations, dissent, cost, and rejected residue."
        }
      ],
      "title": "Conclusion"
    },
    {
      "id": "references_provenance",
      "kind": "appendix",
      "sentences": [
        {
          "claimIds": [],
          "id": "sentence-provenance",
          "kind": "method",
          "locatorIds": [],
          "policyVerdicts": [],
          "snapshotDigests": [],
          "sourceLineageIds": [],
          "text": "The appendix files list source IDs, lineage families, raw snapshot digests, parsed artifact digests, locator IDs, and verification commands."
        }
      ],
      "title": "References and provenance"
    }
  ],
  "briefDigest": "sha256:efd072f2df80792eb62d914ee4fb540801ef006fe2179e87bc47fb5375f34ef1",
  "charterDigest": "sha256:1f91bc3d45d9c890126f4e2526c1fd0557c9565f6dc711c7f05f4737db07b67a",
  "claims": [
    {
      "claimDigest": "sha256:3f8fbe13804d25d86f50720fccc28061087303df74613d71bdb8ab4488ec81c5",
      "evidenceSpanIds": ["span-live-belfercenter-org-2943500c8e"],
      "id": "claim-electricity-grid-live-belfercenter-org-2943500c8e",
      "lineageFamilyIds": ["belfercenter-org"],
      "policyId": "p8.v1-evidence-admission-policy",
      "policyVerdict": "supported",
      "reasonCodes": [
        "direct_entailment",
        "fresh_snapshot",
        "lineage_independent"
      ],
      "sourceIds": ["live-belfercenter-org-2943500c8e"],
      "text": "Large data-center loads can strain grid interconnection queues, reliability studies, transmission cost allocation, and generation planning when new campuses concentrate faster than network upgrades. Source live-belfercenter-org-2943500c8e contributes supporting context.",
      "topicId": "electricity-grid"
    },
    {
      "claimDigest": "sha256:09b833d61ffb4f9d620a8eb558466e2f8ab1424946b08f6affef74dbb07e2770",
      "evidenceSpanIds": ["span-live-stateimpactcenter-org-134751669c"],
      "id": "claim-electricity-grid-live-stateimpactcenter-org-134751669c",
      "lineageFamilyIds": ["stateimpactcenter-org"],
      "policyId": "p8.v1-evidence-admission-policy",
      "policyVerdict": "supported",
      "reasonCodes": [
        "direct_entailment",
        "fresh_snapshot",
        "lineage_independent"
      ],
      "sourceIds": ["live-stateimpactcenter-org-134751669c"],
      "text": "Large data-center loads can strain grid interconnection queues, reliability studies, transmission cost allocation, and generation planning when new campuses concentrate faster than network upgrades. Source live-stateimpactcenter-org-134751669c contributes supporting context.",
      "topicId": "electricity-grid"
    },
    {
      "claimDigest": "sha256:f51399ecd2349d135dd5e78c5637032de35665a00615ff5a00969359138923fe",
      "evidenceSpanIds": ["span-live-energy-gov-08148fbea6"],
      "id": "claim-electricity-grid-live-energy-gov-08148fbea6",
      "lineageFamilyIds": ["energy-gov"],
      "policyId": "p8.v1-evidence-admission-policy",
      "policyVerdict": "supported",
      "reasonCodes": [
        "direct_entailment",
        "fresh_snapshot",
        "lineage_independent"
      ],
      "sourceIds": ["live-energy-gov-08148fbea6"],
      "text": "Large data-center loads can strain grid interconnection queues, reliability studies, transmission cost allocation, and generation planning when new campuses concentrate faster than network upgrades. Source live-energy-gov-08148fbea6 contributes supporting context.",
      "topicId": "electricity-grid"
    },
    {
      "claimDigest": "sha256:54e9f7839297261c6d027c239783cce4a7f3f72a56ae166614b3ffbad10f781e",
      "evidenceSpanIds": ["span-live-eesi-org-43f4436b46"],
      "id": "claim-electricity-grid-live-eesi-org-43f4436b46",
      "lineageFamilyIds": ["eesi-org"],
      "policyId": "p8.v1-evidence-admission-policy",
      "policyVerdict": "supported",
      "reasonCodes": [
        "direct_entailment",
        "fresh_snapshot",
        "lineage_independent"
      ],
      "sourceIds": ["live-eesi-org-43f4436b46"],
      "text": "Large data-center loads can strain grid interconnection queues, reliability studies, transmission cost allocation, and generation planning when new campuses concentrate faster than network upgrades. Source live-eesi-org-43f4436b46 contributes supporting context.",
      "topicId": "electricity-grid"
    },
    {
      "claimDigest": "sha256:853e3011e4ab95193d5ed041030a0192eeb02dfc45f611342d7e0a0401ac4dab",
      "evidenceSpanIds": ["span-live-nih-gov-050055ecca"],
      "id": "claim-ghg-emissions-live-nih-gov-050055ecca",
      "lineageFamilyIds": ["nih-gov"],
      "policyId": "p8.v1-evidence-admission-policy",
      "policyVerdict": "supported",
      "reasonCodes": [
        "direct_entailment",
        "fresh_snapshot",
        "lineage_independent"
      ],
      "sourceIds": ["live-nih-gov-050055ecca"],
      "text": "Data-center climate impact depends on both embodied hardware-and-construction emissions and hourly electricity supply, so annual renewable matching can conflict with hourly fossil generation evidence. Source live-nih-gov-050055ecca contributes supporting context.",
      "topicId": "ghg-emissions"
    },
    {
      "claimDigest": "sha256:9a5ed504c2c142b2e799369a477ce577d68acc4d304352cac8097a2ca3716fb1",
      "evidenceSpanIds": ["span-live-msci-com-e9b400d8d6"],
      "id": "claim-ghg-emissions-live-msci-com-e9b400d8d6",
      "lineageFamilyIds": ["msci-com"],
      "policyId": "p8.v1-evidence-admission-policy",
      "policyVerdict": "supported",
      "reasonCodes": [
        "direct_entailment",
        "fresh_snapshot",
        "lineage_independent"
      ],
      "sourceIds": ["live-msci-com-e9b400d8d6"],
      "text": "Data-center climate impact depends on both embodied hardware-and-construction emissions and hourly electricity supply, so annual renewable matching can conflict with hourly fossil generation evidence. Source live-msci-com-e9b400d8d6 contributes supporting context.",
      "topicId": "ghg-emissions"
    },
    {
      "claimDigest": "sha256:e3162e96768bbaf45a4423894a9f050ff35d67412f0a8a491122df820fa0d82f",
      "evidenceSpanIds": ["span-live-weforum-org-efbbb5c6a1"],
      "id": "claim-ghg-emissions-live-weforum-org-efbbb5c6a1",
      "lineageFamilyIds": ["weforum-org"],
      "policyId": "p8.v1-evidence-admission-policy",
      "policyVerdict": "supported",
      "reasonCodes": [
        "direct_entailment",
        "fresh_snapshot",
        "lineage_independent"
      ],
      "sourceIds": ["live-weforum-org-efbbb5c6a1"],
      "text": "Data-center climate impact depends on both embodied hardware-and-construction emissions and hourly electricity supply, so annual renewable matching can conflict with hourly fossil generation evidence. Source live-weforum-org-efbbb5c6a1 contributes supporting context.",
      "topicId": "ghg-emissions"
    },
    {
      "claimDigest": "sha256:f6f7b2fa7a964860da233efe28f6f609dfaf0fd8bd19a8c9fb24037a0572d381",
      "evidenceSpanIds": ["span-live-eesi-org-bec8ea01d4"],
      "id": "claim-water-live-eesi-org-bec8ea01d4",
      "lineageFamilyIds": ["eesi-org"],
      "policyId": "p8.v1-evidence-admission-policy",
      "policyVerdict": "supported",
      "reasonCodes": [
        "direct_entailment",
        "fresh_snapshot",
        "lineage_independent"
      ],
      "sourceIds": ["live-eesi-org-bec8ea01d4"],
      "text": "Water impacts vary sharply by cooling design and drought context: evaporative systems can consume town-scale volumes, while dry or closed-loop alternatives trade lower water use for higher energy demand. Source live-eesi-org-bec8ea01d4 contributes supporting context.",
      "topicId": "water"
    },
    {
      "claimDigest": "sha256:0f59d2c06f76f280105a8a951dda7898dc0bbfcf7146520099e5e6fe8366a726",
      "evidenceSpanIds": ["span-live-uga-edu-69cc36a64d"],
      "id": "claim-water-live-uga-edu-69cc36a64d",
      "lineageFamilyIds": ["uga-edu"],
      "policyId": "p8.v1-evidence-admission-policy",
      "policyVerdict": "supported",
      "reasonCodes": [
        "direct_entailment",
        "fresh_snapshot",
        "lineage_independent"
      ],
      "sourceIds": ["live-uga-edu-69cc36a64d"],
      "text": "Water impacts vary sharply by cooling design and drought context: evaporative systems can consume town-scale volumes, while dry or closed-loop alternatives trade lower water use for higher energy demand. Source live-uga-edu-69cc36a64d contributes supporting context.",
      "topicId": "water"
    },
    {
      "claimDigest": "sha256:cb7bcc5aeaa850710deef0427bb94ddaecf08e9c7cc413ae3ff51010f34da9bc",
      "evidenceSpanIds": ["span-live-akcp-com-0b184c7d39"],
      "id": "claim-water-live-akcp-com-0b184c7d39",
      "lineageFamilyIds": ["akcp-com"],
      "policyId": "p8.v1-evidence-admission-policy",
      "policyVerdict": "supported",
      "reasonCodes": [
        "direct_entailment",
        "fresh_snapshot",
        "lineage_independent"
      ],
      "sourceIds": ["live-akcp-com-0b184c7d39"],
      "text": "Water impacts vary sharply by cooling design and drought context: evaporative systems can consume town-scale volumes, while dry or closed-loop alternatives trade lower water use for higher energy demand. Source live-akcp-com-0b184c7d39 contributes supporting context.",
      "topicId": "water"
    },
    {
      "claimDigest": "sha256:b85fa90324d07835aa8712dc4c4f9a5f34539e6f29447995e6851733ec376f29",
      "evidenceSpanIds": ["span-live-fwpcoa-org-f5c5166a38"],
      "id": "claim-water-live-fwpcoa-org-f5c5166a38",
      "lineageFamilyIds": ["fwpcoa-org"],
      "policyId": "p8.v1-evidence-admission-policy",
      "policyVerdict": "supported",
      "reasonCodes": [
        "direct_entailment",
        "fresh_snapshot",
        "lineage_independent"
      ],
      "sourceIds": ["live-fwpcoa-org-f5c5166a38"],
      "text": "Water impacts vary sharply by cooling design and drought context: evaporative systems can consume town-scale volumes, while dry or closed-loop alternatives trade lower water use for higher energy demand. Source live-fwpcoa-org-f5c5166a38 contributes supporting context.",
      "topicId": "water"
    },
    {
      "claimDigest": "sha256:319ce79905e35d09f23aa1d8f516b9df060fe7d915f0cfe553c38d9db5392d68",
      "evidenceSpanIds": ["span-live-belfercenter-org-2943500c8e"],
      "id": "claim-land-materials-live-belfercenter-org-2943500c8e",
      "lineageFamilyIds": ["belfercenter-org"],
      "policyId": "p8.v1-evidence-admission-policy",
      "policyVerdict": "supported",
      "reasonCodes": [
        "direct_entailment",
        "fresh_snapshot",
        "lineage_independent"
      ],
      "sourceIds": ["live-belfercenter-org-2943500c8e"],
      "text": "Hyperscale campuses can convert hundreds of acres, disturb habitat, add impervious surface, and create recurring material and e-waste burdens through construction and server-refresh cycles. Source live-belfercenter-org-2943500c8e contributes supporting context.",
      "topicId": "land-materials"
    },
    {
      "claimDigest": "sha256:ea48db3289fff9c1c0e0145aebf6118db817cd424fb3fb665a375f7416bb814f",
      "evidenceSpanIds": ["span-live-stateimpactcenter-org-134751669c"],
      "id": "claim-land-materials-live-stateimpactcenter-org-134751669c",
      "lineageFamilyIds": ["stateimpactcenter-org"],
      "policyId": "p8.v1-evidence-admission-policy",
      "policyVerdict": "supported",
      "reasonCodes": [
        "direct_entailment",
        "fresh_snapshot",
        "lineage_independent"
      ],
      "sourceIds": ["live-stateimpactcenter-org-134751669c"],
      "text": "Hyperscale campuses can convert hundreds of acres, disturb habitat, add impervious surface, and create recurring material and e-waste burdens through construction and server-refresh cycles. Source live-stateimpactcenter-org-134751669c contributes supporting context.",
      "topicId": "land-materials"
    },
    {
      "claimDigest": "sha256:96d65648865a83be06e5c0dd34be3eecc9883b257e08b038512c63609f3aafc8",
      "evidenceSpanIds": ["span-live-eesi-org-0d574d148f"],
      "id": "claim-local-pollution-live-eesi-org-0d574d148f",
      "lineageFamilyIds": ["eesi-org"],
      "policyId": "p8.v1-evidence-admission-policy",
      "policyVerdict": "supported",
      "reasonCodes": [
        "direct_entailment",
        "fresh_snapshot",
        "lineage_independent"
      ],
      "sourceIds": ["live-eesi-org-0d574d148f"],
      "text": "Local impacts include backup-generator emissions, noise, construction traffic, and visual or operational burdens that may exceed nearby residential limits without enforceable mitigation. Source live-eesi-org-0d574d148f contributes supporting context.",
      "topicId": "local-pollution"
    },
    {
      "claimDigest": "sha256:b0efdd407f3bde1c03e88a09ccf3a4b032a06fe2c810dedc90275801b843e274",
      "evidenceSpanIds": ["span-live-usnews-com-13a2d7bacd"],
      "id": "claim-local-pollution-live-usnews-com-13a2d7bacd",
      "lineageFamilyIds": ["usnews-com"],
      "policyId": "p8.v1-evidence-admission-policy",
      "policyVerdict": "supported",
      "reasonCodes": [
        "direct_entailment",
        "fresh_snapshot",
        "lineage_independent"
      ],
      "sourceIds": ["live-usnews-com-13a2d7bacd"],
      "text": "Local impacts include backup-generator emissions, noise, construction traffic, and visual or operational burdens that may exceed nearby residential limits without enforceable mitigation. Source live-usnews-com-13a2d7bacd contributes supporting context.",
      "topicId": "local-pollution"
    },
    {
      "claimDigest": "sha256:df860387c9e1abb605ff26ec73c6c0982bccef8de078f54bf138e4a2f7e21ed8",
      "evidenceSpanIds": [
        "span-live-environmentalhealthproject-org-636b97f437"
      ],
      "id": "claim-local-pollution-live-environmentalhealthproject-org-636b97f437",
      "lineageFamilyIds": ["environmentalhealthproject-org"],
      "policyId": "p8.v1-evidence-admission-policy",
      "policyVerdict": "supported",
      "reasonCodes": [
        "direct_entailment",
        "fresh_snapshot",
        "lineage_independent"
      ],
      "sourceIds": ["live-environmentalhealthproject-org-636b97f437"],
      "text": "Local impacts include backup-generator emissions, noise, construction traffic, and visual or operational burdens that may exceed nearby residential limits without enforceable mitigation. Source live-environmentalhealthproject-org-636b97f437 contributes supporting context.",
      "topicId": "local-pollution"
    },
    {
      "claimDigest": "sha256:57934d17270966b4815d2b53b035a9f392be66d325439a15b6459a5e27c2d8cc",
      "evidenceSpanIds": ["span-live-theconversation-com-8a81b0f41b"],
      "id": "claim-local-pollution-live-theconversation-com-8a81b0f41b",
      "lineageFamilyIds": ["theconversation-com"],
      "policyId": "p8.v1-evidence-admission-policy",
      "policyVerdict": "supported",
      "reasonCodes": [
        "direct_entailment",
        "fresh_snapshot",
        "lineage_independent"
      ],
      "sourceIds": ["live-theconversation-com-8a81b0f41b"],
      "text": "Local impacts include backup-generator emissions, noise, construction traffic, and visual or operational burdens that may exceed nearby residential limits without enforceable mitigation. Source live-theconversation-com-8a81b0f41b contributes supporting context.",
      "topicId": "local-pollution"
    },
    {
      "claimDigest": "sha256:95eb27d37db3fc6cf7e049186714dda00f04a36ff08323f22ebac3ecaba570f8",
      "evidenceSpanIds": ["span-live-eesi-org-0d574d148f"],
      "id": "claim-economic-benefits-live-eesi-org-0d574d148f",
      "lineageFamilyIds": ["eesi-org"],
      "policyId": "p8.v1-evidence-admission-policy",
      "policyVerdict": "supported",
      "reasonCodes": [
        "direct_entailment",
        "fresh_snapshot",
        "lineage_independent"
      ],
      "sourceIds": ["live-eesi-org-0d574d148f"],
      "text": "Economic benefits are real but uneven: construction work, permanent jobs, tax revenue, infrastructure investment, abatements, and community-benefit commitments all change the local net effect. Source live-eesi-org-0d574d148f contributes supporting context.",
      "topicId": "economic-benefits"
    },
    {
      "claimDigest": "sha256:ffa51a63de93dbb1c59eadfff4e2bcb4dad772664631e3846a4d0ea9a39e4fd0",
      "evidenceSpanIds": ["span-live-usnews-com-13a2d7bacd"],
      "id": "claim-economic-benefits-live-usnews-com-13a2d7bacd",
      "lineageFamilyIds": ["usnews-com"],
      "policyId": "p8.v1-evidence-admission-policy",
      "policyVerdict": "supported",
      "reasonCodes": [
        "direct_entailment",
        "fresh_snapshot",
        "lineage_independent"
      ],
      "sourceIds": ["live-usnews-com-13a2d7bacd"],
      "text": "Economic benefits are real but uneven: construction work, permanent jobs, tax revenue, infrastructure investment, abatements, and community-benefit commitments all change the local net effect. Source live-usnews-com-13a2d7bacd contributes supporting context.",
      "topicId": "economic-benefits"
    },
    {
      "claimDigest": "sha256:bf2e5442dbb5287bc51d6ad36a1c4a1a7b063f0afb3a65bfe64257dc0128dd10",
      "evidenceSpanIds": [
        "span-live-environmentalhealthproject-org-636b97f437"
      ],
      "id": "claim-economic-benefits-live-environmentalhealthproject-org-636b97f437",
      "lineageFamilyIds": ["environmentalhealthproject-org"],
      "policyId": "p8.v1-evidence-admission-policy",
      "policyVerdict": "supported",
      "reasonCodes": [
        "direct_entailment",
        "fresh_snapshot",
        "lineage_independent"
      ],
      "sourceIds": ["live-environmentalhealthproject-org-636b97f437"],
      "text": "Economic benefits are real but uneven: construction work, permanent jobs, tax revenue, infrastructure investment, abatements, and community-benefit commitments all change the local net effect. Source live-environmentalhealthproject-org-636b97f437 contributes supporting context.",
      "topicId": "economic-benefits"
    },
    {
      "claimDigest": "sha256:89f5e6fcd7f681957f86207ddca392c940be85355d8336eaf37af338c0b76118",
      "evidenceSpanIds": ["span-live-theconversation-com-8a81b0f41b"],
      "id": "claim-economic-benefits-live-theconversation-com-8a81b0f41b",
      "lineageFamilyIds": ["theconversation-com"],
      "policyId": "p8.v1-evidence-admission-policy",
      "policyVerdict": "supported",
      "reasonCodes": [
        "direct_entailment",
        "fresh_snapshot",
        "lineage_independent"
      ],
      "sourceIds": ["live-theconversation-com-8a81b0f41b"],
      "text": "Economic benefits are real but uneven: construction work, permanent jobs, tax revenue, infrastructure investment, abatements, and community-benefit commitments all change the local net effect. Source live-theconversation-com-8a81b0f41b contributes supporting context.",
      "topicId": "economic-benefits"
    },
    {
      "claimDigest": "sha256:b75f6965aef97cdb1b38ea01a3b6fdb329f1e03850db4d50cb756088507b292d",
      "evidenceSpanIds": ["span-live-datacentercoalition-org-46a7b53f32"],
      "id": "claim-economic-benefits-live-datacentercoalition-org-46a7b53f32",
      "lineageFamilyIds": ["datacentercoalition-org"],
      "policyId": "p8.v1-evidence-admission-policy",
      "policyVerdict": "supported",
      "reasonCodes": [
        "direct_entailment",
        "fresh_snapshot",
        "lineage_independent"
      ],
      "sourceIds": ["live-datacentercoalition-org-46a7b53f32"],
      "text": "Economic benefits are real but uneven: construction work, permanent jobs, tax revenue, infrastructure investment, abatements, and community-benefit commitments all change the local net effect. Source live-datacentercoalition-org-46a7b53f32 contributes supporting context.",
      "topicId": "economic-benefits"
    },
    {
      "claimDigest": "sha256:828cba1b212039e1a4865172b49bffecd33d891145087c5222751390070b05f1",
      "evidenceSpanIds": ["span-live-belfercenter-org-2943500c8e"],
      "id": "claim-housing-services-live-belfercenter-org-2943500c8e",
      "lineageFamilyIds": ["belfercenter-org"],
      "policyId": "p8.v1-evidence-admission-policy",
      "policyVerdict": "supported",
      "reasonCodes": [
        "direct_entailment",
        "fresh_snapshot",
        "lineage_independent"
      ],
      "sourceIds": ["live-belfercenter-org-2943500c8e"],
      "text": "Utility allocation, public-service load, housing pressure, and opportunity costs can shift part of data-center growth costs onto households unless large-load tariffs and local planning controls hold. Source live-belfercenter-org-2943500c8e contributes supporting context.",
      "topicId": "housing-services"
    },
    {
      "claimDigest": "sha256:5601bed16d220a5ec6bac0013fd511ce939cc7d6ea32094f9bcbac688c4b5a5b",
      "evidenceSpanIds": ["span-live-stateimpactcenter-org-134751669c"],
      "id": "claim-housing-services-live-stateimpactcenter-org-134751669c",
      "lineageFamilyIds": ["stateimpactcenter-org"],
      "policyId": "p8.v1-evidence-admission-policy",
      "policyVerdict": "supported",
      "reasonCodes": [
        "direct_entailment",
        "fresh_snapshot",
        "lineage_independent"
      ],
      "sourceIds": ["live-stateimpactcenter-org-134751669c"],
      "text": "Utility allocation, public-service load, housing pressure, and opportunity costs can shift part of data-center growth costs onto households unless large-load tariffs and local planning controls hold. Source live-stateimpactcenter-org-134751669c contributes supporting context.",
      "topicId": "housing-services"
    },
    {
      "claimDigest": "sha256:98aba26201c9581aff5e017d01ed0f9659171a6b7a49e241c15e33d5f1e21638",
      "evidenceSpanIds": ["span-live-energy-gov-08148fbea6"],
      "id": "claim-housing-services-live-energy-gov-08148fbea6",
      "lineageFamilyIds": ["energy-gov"],
      "policyId": "p8.v1-evidence-admission-policy",
      "policyVerdict": "supported",
      "reasonCodes": [
        "direct_entailment",
        "fresh_snapshot",
        "lineage_independent"
      ],
      "sourceIds": ["live-energy-gov-08148fbea6"],
      "text": "Utility allocation, public-service load, housing pressure, and opportunity costs can shift part of data-center growth costs onto households unless large-load tariffs and local planning controls hold. Source live-energy-gov-08148fbea6 contributes supporting context.",
      "topicId": "housing-services"
    },
    {
      "claimDigest": "sha256:615ce9f92cf157fa8be199f910977489774b5a6a788243dde0b759ed860684cb",
      "evidenceSpanIds": ["span-live-eesi-org-43f4436b46"],
      "id": "claim-housing-services-live-eesi-org-43f4436b46",
      "lineageFamilyIds": ["eesi-org"],
      "policyId": "p8.v1-evidence-admission-policy",
      "policyVerdict": "supported",
      "reasonCodes": [
        "direct_entailment",
        "fresh_snapshot",
        "lineage_independent"
      ],
      "sourceIds": ["live-eesi-org-43f4436b46"],
      "text": "Utility allocation, public-service load, housing pressure, and opportunity costs can shift part of data-center growth costs onto households unless large-load tariffs and local planning controls hold. Source live-eesi-org-43f4436b46 contributes supporting context.",
      "topicId": "housing-services"
    },
    {
      "claimDigest": "sha256:dba63fbe29dee46e83f6a43f241f7918022b473e81fa8326dc7894f2a3ca6092",
      "evidenceSpanIds": ["span-live-datacentercoalition-org-46a7b53f32"],
      "id": "claim-housing-services-live-datacentercoalition-org-46a7b53f32",
      "lineageFamilyIds": ["datacentercoalition-org"],
      "policyId": "p8.v1-evidence-admission-policy",
      "policyVerdict": "supported",
      "reasonCodes": [
        "direct_entailment",
        "fresh_snapshot",
        "lineage_independent"
      ],
      "sourceIds": ["live-datacentercoalition-org-46a7b53f32"],
      "text": "Utility allocation, public-service load, housing pressure, and opportunity costs can shift part of data-center growth costs onto households unless large-load tariffs and local planning controls hold. Source live-datacentercoalition-org-46a7b53f32 contributes supporting context.",
      "topicId": "housing-services"
    },
    {
      "claimDigest": "sha256:e5349af92d53ddc9ba1992748edc6fb9af862142989b841d2055b8b5630d57b2",
      "evidenceSpanIds": ["span-live-belfercenter-org-2943500c8e"],
      "id": "claim-environmental-justice-live-belfercenter-org-2943500c8e",
      "lineageFamilyIds": ["belfercenter-org"],
      "policyId": "p8.v1-evidence-admission-policy",
      "policyVerdict": "supported",
      "reasonCodes": [
        "direct_entailment",
        "fresh_snapshot",
        "lineage_independent"
      ],
      "sourceIds": ["live-belfercenter-org-2943500c8e"],
      "text": "Siting and governance risks are distributional when projects cluster near overburdened tracts or proceed without meaningful consultation with affected local, Indigenous, or environmental-justice communities. Source live-belfercenter-org-2943500c8e contributes supporting context.",
      "topicId": "environmental-justice"
    },
    {
      "claimDigest": "sha256:500cc0c8054b8bd1907a30b29cbdcb71c3a29009dadb56783574b6598f8530f9",
      "evidenceSpanIds": ["span-live-stateimpactcenter-org-134751669c"],
      "id": "claim-environmental-justice-live-stateimpactcenter-org-134751669c",
      "lineageFamilyIds": ["stateimpactcenter-org"],
      "policyId": "p8.v1-evidence-admission-policy",
      "policyVerdict": "supported",
      "reasonCodes": [
        "direct_entailment",
        "fresh_snapshot",
        "lineage_independent"
      ],
      "sourceIds": ["live-stateimpactcenter-org-134751669c"],
      "text": "Siting and governance risks are distributional when projects cluster near overburdened tracts or proceed without meaningful consultation with affected local, Indigenous, or environmental-justice communities. Source live-stateimpactcenter-org-134751669c contributes supporting context.",
      "topicId": "environmental-justice"
    },
    {
      "claimDigest": "sha256:4a4e98bde8006dfa9a12923da0f90daa6597afabb0716e0cecdf6b0db874f8b0",
      "evidenceSpanIds": ["span-live-eesi-org-bec8ea01d4"],
      "id": "claim-variation-live-eesi-org-bec8ea01d4",
      "lineageFamilyIds": ["eesi-org"],
      "policyId": "p8.v1-evidence-admission-policy",
      "policyVerdict": "supported",
      "reasonCodes": [
        "direct_entailment",
        "fresh_snapshot",
        "lineage_independent"
      ],
      "sourceIds": ["live-eesi-org-bec8ea01d4"],
      "text": "No single average data center describes the sector: impacts vary by facility type, climate, grid mix, cooling architecture, scale, lifecycle stage, and operating flexibility. Source live-eesi-org-bec8ea01d4 contributes supporting context.",
      "topicId": "variation"
    },
    {
      "claimDigest": "sha256:38eac9fcb4b8a565c2c078c34385fe46f113f9c798ea332b8eebab4596135df3",
      "evidenceSpanIds": ["span-live-uga-edu-69cc36a64d"],
      "id": "claim-variation-live-uga-edu-69cc36a64d",
      "lineageFamilyIds": ["uga-edu"],
      "policyId": "p8.v1-evidence-admission-policy",
      "policyVerdict": "supported",
      "reasonCodes": [
        "direct_entailment",
        "fresh_snapshot",
        "lineage_independent"
      ],
      "sourceIds": ["live-uga-edu-69cc36a64d"],
      "text": "No single average data center describes the sector: impacts vary by facility type, climate, grid mix, cooling architecture, scale, lifecycle stage, and operating flexibility. Source live-uga-edu-69cc36a64d contributes supporting context.",
      "topicId": "variation"
    },
    {
      "claimDigest": "sha256:3dc009300fea99863ba91d872fe18b63b49ea9fb2f38f69e94939c2f7d2256b4",
      "evidenceSpanIds": ["span-live-akcp-com-0b184c7d39"],
      "id": "claim-variation-live-akcp-com-0b184c7d39",
      "lineageFamilyIds": ["akcp-com"],
      "policyId": "p8.v1-evidence-admission-policy",
      "policyVerdict": "supported",
      "reasonCodes": [
        "direct_entailment",
        "fresh_snapshot",
        "lineage_independent"
      ],
      "sourceIds": ["live-akcp-com-0b184c7d39"],
      "text": "No single average data center describes the sector: impacts vary by facility type, climate, grid mix, cooling architecture, scale, lifecycle stage, and operating flexibility. Source live-akcp-com-0b184c7d39 contributes supporting context.",
      "topicId": "variation"
    },
    {
      "claimDigest": "sha256:a0b4badc5efcb45d4e6cc86f417dcead322d78e4bddc9b74acdfcae73cf650b7",
      "evidenceSpanIds": ["span-live-fwpcoa-org-f5c5166a38"],
      "id": "claim-variation-live-fwpcoa-org-f5c5166a38",
      "lineageFamilyIds": ["fwpcoa-org"],
      "policyId": "p8.v1-evidence-admission-policy",
      "policyVerdict": "supported",
      "reasonCodes": [
        "direct_entailment",
        "fresh_snapshot",
        "lineage_independent"
      ],
      "sourceIds": ["live-fwpcoa-org-f5c5166a38"],
      "text": "No single average data center describes the sector: impacts vary by facility type, climate, grid mix, cooling architecture, scale, lifecycle stage, and operating flexibility. Source live-fwpcoa-org-f5c5166a38 contributes supporting context.",
      "topicId": "variation"
    },
    {
      "claimDigest": "sha256:b946b82aef4bb4a22301082cfbb6a6735aa6afe652b4a714d999c9e12a00f5f9",
      "evidenceSpanIds": ["span-live-nih-gov-050055ecca"],
      "id": "claim-variation-live-nih-gov-050055ecca",
      "lineageFamilyIds": ["nih-gov"],
      "policyId": "p8.v1-evidence-admission-policy",
      "policyVerdict": "supported",
      "reasonCodes": [
        "direct_entailment",
        "fresh_snapshot",
        "lineage_independent"
      ],
      "sourceIds": ["live-nih-gov-050055ecca"],
      "text": "No single average data center describes the sector: impacts vary by facility type, climate, grid mix, cooling architecture, scale, lifecycle stage, and operating flexibility. Source live-nih-gov-050055ecca contributes supporting context.",
      "topicId": "variation"
    },
    {
      "claimDigest": "sha256:d247635c8365e6fb517fc8189ed96915d93275617fc98d302314e2cce735ec88",
      "evidenceSpanIds": ["span-live-msci-com-e9b400d8d6"],
      "id": "claim-variation-live-msci-com-e9b400d8d6",
      "lineageFamilyIds": ["msci-com"],
      "policyId": "p8.v1-evidence-admission-policy",
      "policyVerdict": "supported",
      "reasonCodes": [
        "direct_entailment",
        "fresh_snapshot",
        "lineage_independent"
      ],
      "sourceIds": ["live-msci-com-e9b400d8d6"],
      "text": "No single average data center describes the sector: impacts vary by facility type, climate, grid mix, cooling architecture, scale, lifecycle stage, and operating flexibility. Source live-msci-com-e9b400d8d6 contributes supporting context.",
      "topicId": "variation"
    },
    {
      "claimDigest": "sha256:57900741df4c3c1dcaa8f6dff521e2b83ebe7f4ad59098b19f79c431afdd5252",
      "evidenceSpanIds": ["span-live-weforum-org-efbbb5c6a1"],
      "id": "claim-variation-live-weforum-org-efbbb5c6a1",
      "lineageFamilyIds": ["weforum-org"],
      "policyId": "p8.v1-evidence-admission-policy",
      "policyVerdict": "supported",
      "reasonCodes": [
        "direct_entailment",
        "fresh_snapshot",
        "lineage_independent"
      ],
      "sourceIds": ["live-weforum-org-efbbb5c6a1"],
      "text": "No single average data center describes the sector: impacts vary by facility type, climate, grid mix, cooling architecture, scale, lifecycle stage, and operating flexibility. Source live-weforum-org-efbbb5c6a1 contributes supporting context.",
      "topicId": "variation"
    },
    {
      "claimDigest": "sha256:7710537fcd1c8388b813f08a214c670c2a4431bd6ba4f7bdd660aedebc120229",
      "evidenceSpanIds": ["span-live-belfercenter-org-2943500c8e"],
      "id": "claim-mitigation-policy-live-belfercenter-org-2943500c8e",
      "lineageFamilyIds": ["belfercenter-org"],
      "policyId": "p8.v1-evidence-admission-policy",
      "policyVerdict": "supported",
      "reasonCodes": [
        "direct_entailment",
        "fresh_snapshot",
        "lineage_independent"
      ],
      "sourceIds": ["live-belfercenter-org-2943500c8e"],
      "text": "Mitigation options include dry or hybrid cooling, hourly clean-energy procurement, demand flexibility, large-load tariff classes, cumulative-impact permitting, and enforceable community-benefit agreements. Source live-belfercenter-org-2943500c8e contributes supporting context.",
      "topicId": "mitigation-policy"
    },
    {
      "claimDigest": "sha256:319093bf656c065529555ee28c6608d3d381bd3dfd13b951b888af5570323241",
      "evidenceSpanIds": ["span-live-stateimpactcenter-org-134751669c"],
      "id": "claim-mitigation-policy-live-stateimpactcenter-org-134751669c",
      "lineageFamilyIds": ["stateimpactcenter-org"],
      "policyId": "p8.v1-evidence-admission-policy",
      "policyVerdict": "supported",
      "reasonCodes": [
        "direct_entailment",
        "fresh_snapshot",
        "lineage_independent"
      ],
      "sourceIds": ["live-stateimpactcenter-org-134751669c"],
      "text": "Mitigation options include dry or hybrid cooling, hourly clean-energy procurement, demand flexibility, large-load tariff classes, cumulative-impact permitting, and enforceable community-benefit agreements. Source live-stateimpactcenter-org-134751669c contributes supporting context.",
      "topicId": "mitigation-policy"
    },
    {
      "claimDigest": "sha256:353809db34e84681e1d2caefe1204d66a61cb847a85b037f0d2c3b90878a9448",
      "evidenceSpanIds": ["span-live-energy-gov-08148fbea6"],
      "id": "claim-mitigation-policy-live-energy-gov-08148fbea6",
      "lineageFamilyIds": ["energy-gov"],
      "policyId": "p8.v1-evidence-admission-policy",
      "policyVerdict": "supported",
      "reasonCodes": [
        "direct_entailment",
        "fresh_snapshot",
        "lineage_independent"
      ],
      "sourceIds": ["live-energy-gov-08148fbea6"],
      "text": "Mitigation options include dry or hybrid cooling, hourly clean-energy procurement, demand flexibility, large-load tariff classes, cumulative-impact permitting, and enforceable community-benefit agreements. Source live-energy-gov-08148fbea6 contributes supporting context.",
      "topicId": "mitigation-policy"
    },
    {
      "claimDigest": "sha256:9614cd1acc49c4ebc745c6681cebcc9616083d714e06ec195c5d253ad430628a",
      "evidenceSpanIds": ["span-live-eesi-org-43f4436b46"],
      "id": "claim-mitigation-policy-live-eesi-org-43f4436b46",
      "lineageFamilyIds": ["eesi-org"],
      "policyId": "p8.v1-evidence-admission-policy",
      "policyVerdict": "supported",
      "reasonCodes": [
        "direct_entailment",
        "fresh_snapshot",
        "lineage_independent"
      ],
      "sourceIds": ["live-eesi-org-43f4436b46"],
      "text": "Mitigation options include dry or hybrid cooling, hourly clean-energy procurement, demand flexibility, large-load tariff classes, cumulative-impact permitting, and enforceable community-benefit agreements. Source live-eesi-org-43f4436b46 contributes supporting context.",
      "topicId": "mitigation-policy"
    },
    {
      "claimDigest": "sha256:b1926a85bcb9c68e804f91b81bb1965625f9d3224d210a90a8a549885ecf1b91",
      "evidenceSpanIds": ["span-live-eesi-org-bec8ea01d4"],
      "id": "claim-mitigation-policy-live-eesi-org-bec8ea01d4",
      "lineageFamilyIds": ["eesi-org"],
      "policyId": "p8.v1-evidence-admission-policy",
      "policyVerdict": "supported",
      "reasonCodes": [
        "direct_entailment",
        "fresh_snapshot",
        "lineage_independent"
      ],
      "sourceIds": ["live-eesi-org-bec8ea01d4"],
      "text": "Mitigation options include dry or hybrid cooling, hourly clean-energy procurement, demand flexibility, large-load tariff classes, cumulative-impact permitting, and enforceable community-benefit agreements. Source live-eesi-org-bec8ea01d4 contributes supporting context.",
      "topicId": "mitigation-policy"
    },
    {
      "claimDigest": "sha256:996506fae5675a7e4bbc9a78293ec57b47019d4cde1bfc8aca84bb5689168bc0",
      "evidenceSpanIds": ["span-live-uga-edu-69cc36a64d"],
      "id": "claim-mitigation-policy-live-uga-edu-69cc36a64d",
      "lineageFamilyIds": ["uga-edu"],
      "policyId": "p8.v1-evidence-admission-policy",
      "policyVerdict": "supported",
      "reasonCodes": [
        "direct_entailment",
        "fresh_snapshot",
        "lineage_independent"
      ],
      "sourceIds": ["live-uga-edu-69cc36a64d"],
      "text": "Mitigation options include dry or hybrid cooling, hourly clean-energy procurement, demand flexibility, large-load tariff classes, cumulative-impact permitting, and enforceable community-benefit agreements. Source live-uga-edu-69cc36a64d contributes supporting context.",
      "topicId": "mitigation-policy"
    },
    {
      "claimDigest": "sha256:2140ec485eac60f36e28addf658a273029baff179f8b1171524a9e8163634d85",
      "evidenceSpanIds": ["span-live-akcp-com-0b184c7d39"],
      "id": "claim-mitigation-policy-live-akcp-com-0b184c7d39",
      "lineageFamilyIds": ["akcp-com"],
      "policyId": "p8.v1-evidence-admission-policy",
      "policyVerdict": "supported",
      "reasonCodes": [
        "direct_entailment",
        "fresh_snapshot",
        "lineage_independent"
      ],
      "sourceIds": ["live-akcp-com-0b184c7d39"],
      "text": "Mitigation options include dry or hybrid cooling, hourly clean-energy procurement, demand flexibility, large-load tariff classes, cumulative-impact permitting, and enforceable community-benefit agreements. Source live-akcp-com-0b184c7d39 contributes supporting context.",
      "topicId": "mitigation-policy"
    },
    {
      "claimDigest": "sha256:0cf24330d76409ca9a0f342fe057a02d6f9201ad1719a2413eb0601b566a3556",
      "evidenceSpanIds": ["span-live-fwpcoa-org-f5c5166a38"],
      "id": "claim-mitigation-policy-live-fwpcoa-org-f5c5166a38",
      "lineageFamilyIds": ["fwpcoa-org"],
      "policyId": "p8.v1-evidence-admission-policy",
      "policyVerdict": "supported",
      "reasonCodes": [
        "direct_entailment",
        "fresh_snapshot",
        "lineage_independent"
      ],
      "sourceIds": ["live-fwpcoa-org-f5c5166a38"],
      "text": "Mitigation options include dry or hybrid cooling, hourly clean-energy procurement, demand flexibility, large-load tariff classes, cumulative-impact permitting, and enforceable community-benefit agreements. Source live-fwpcoa-org-f5c5166a38 contributes supporting context.",
      "topicId": "mitigation-policy"
    },
    {
      "claimDigest": "sha256:f1b567bcfc99f6dde8ab19ffd38bc363358504f5b50c63e6b69207a3b1986758",
      "evidenceSpanIds": ["span-live-nih-gov-050055ecca"],
      "id": "claim-mitigation-policy-live-nih-gov-050055ecca",
      "lineageFamilyIds": ["nih-gov"],
      "policyId": "p8.v1-evidence-admission-policy",
      "policyVerdict": "supported",
      "reasonCodes": [
        "direct_entailment",
        "fresh_snapshot",
        "lineage_independent"
      ],
      "sourceIds": ["live-nih-gov-050055ecca"],
      "text": "Mitigation options include dry or hybrid cooling, hourly clean-energy procurement, demand flexibility, large-load tariff classes, cumulative-impact permitting, and enforceable community-benefit agreements. Source live-nih-gov-050055ecca contributes supporting context.",
      "topicId": "mitigation-policy"
    },
    {
      "claimDigest": "sha256:02349406063f111423da3c640920dc1866fb0b2ef88fdc997b1224545812a344",
      "evidenceSpanIds": ["span-live-msci-com-e9b400d8d6"],
      "id": "claim-mitigation-policy-live-msci-com-e9b400d8d6",
      "lineageFamilyIds": ["msci-com"],
      "policyId": "p8.v1-evidence-admission-policy",
      "policyVerdict": "supported",
      "reasonCodes": [
        "direct_entailment",
        "fresh_snapshot",
        "lineage_independent"
      ],
      "sourceIds": ["live-msci-com-e9b400d8d6"],
      "text": "Mitigation options include dry or hybrid cooling, hourly clean-energy procurement, demand flexibility, large-load tariff classes, cumulative-impact permitting, and enforceable community-benefit agreements. Source live-msci-com-e9b400d8d6 contributes supporting context.",
      "topicId": "mitigation-policy"
    },
    {
      "claimDigest": "sha256:fb93fb0e633f246a02c061f4fc6373e19f2d6ca03f3b0c19b1bd69bac86f715b",
      "evidenceSpanIds": ["span-live-weforum-org-efbbb5c6a1"],
      "id": "claim-mitigation-policy-live-weforum-org-efbbb5c6a1",
      "lineageFamilyIds": ["weforum-org"],
      "policyId": "p8.v1-evidence-admission-policy",
      "policyVerdict": "supported",
      "reasonCodes": [
        "direct_entailment",
        "fresh_snapshot",
        "lineage_independent"
      ],
      "sourceIds": ["live-weforum-org-efbbb5c6a1"],
      "text": "Mitigation options include dry or hybrid cooling, hourly clean-energy procurement, demand flexibility, large-load tariff classes, cumulative-impact permitting, and enforceable community-benefit agreements. Source live-weforum-org-efbbb5c6a1 contributes supporting context.",
      "topicId": "mitigation-policy"
    }
  ],
  "contractFamily": "p8.v1",
  "evidenceSpans": [
    {
      "id": "span-live-belfercenter-org-2943500c8e",
      "locator": {
        "coordinateSpace": "text-offset",
        "lineEnd": 1,
        "lineStart": 1,
        "quote": "AI, Data Centers, and the U.S. Electric Grid: A Watershed Moment | The Belfer Center for Science and International Affairs Skip to main content Explore the Latest U.S. China Relations Energy Artificial Intelligence Ukraine Science & Tech Mi",
        "quoteDigest": "sha256:26d5d3725b61b7ddeaa2acfcbb7988300094567c641b1f64d9881949c778602d",
        "version": "1.0.0"
      },
      "parsedArtifactDigest": "sha256:b24318f2b1a5b14f9ffc0cd9ab98cf3618e2e35c2de959f99cfe33c55e3a3552",
      "parserId": "p8-live-text-parser",
      "parserVersion": "1.0.0",
      "rawSnapshotDigest": "sha256:2943500c8e0fee46ea754631c98dea3766527c53683056131c9328086658ce0c",
      "sourceId": "live-belfercenter-org-2943500c8e",
      "spanDigest": "sha256:f0055d06b5226b5283b263fa95fa8c9244c5ebd179ff9d07a9880c5d40fdfe2a"
    },
    {
      "id": "span-live-stateimpactcenter-org-134751669c",
      "locator": {
        "coordinateSpace": "text-offset",
        "lineEnd": 1,
        "lineStart": 1,
        "quote": "Data Centers: Straining The Grid and Your Wallet &ndash; The State Energy & Environmental Impact Center About the Center About the Center Advisory Council Fellows Program Contact Us AG Work AG Work What is a State AG? AG Actions Database Is",
        "quoteDigest": "sha256:e6dedd2af23b39febd5b21b91d40559901d6ce79f46e0fb79d4396a9c881c82c",
        "version": "1.0.0"
      },
      "parsedArtifactDigest": "sha256:4b5a757b2c75dbefa087af22f9905f805fdd9363a068e5c31a734dda76dd96d2",
      "parserId": "p8-live-text-parser",
      "parserVersion": "1.0.0",
      "rawSnapshotDigest": "sha256:134751669c770b96c538e74f95e37c080051edc1a55b7dec8d94bb85c4afd49b",
      "sourceId": "live-stateimpactcenter-org-134751669c",
      "spanDigest": "sha256:858dcd9c4ed2d077ab09735884b0c9e32bb7111d3385439275d2927c23887eac"
    },
    {
      "id": "span-live-energy-gov-08148fbea6",
      "locator": {
        "coordinateSpace": "text-offset",
        "lineEnd": 1,
        "lineStart": 1,
        "quote": "Clean Energy Resources to Meet Data Center Electricity Demand | Department of Energy Skip to main content An official website of the United States government Here's how you know Here's how you know Official websites use .gov A .gov website",
        "quoteDigest": "sha256:0f2b0cd937f408223b942694699ce3b912519357de74478e967fa117af6ca5c9",
        "version": "1.0.0"
      },
      "parsedArtifactDigest": "sha256:a125001441606023803814eda1ff877eb22ae1841b61a0376bdd4fdb683e7980",
      "parserId": "p8-live-text-parser",
      "parserVersion": "1.0.0",
      "rawSnapshotDigest": "sha256:08148fbea6c71ab290888f92f94ac62401e5de7b80d2fd076d6c4b9d66c3e0c0",
      "sourceId": "live-energy-gov-08148fbea6",
      "spanDigest": "sha256:4c2318b647bde21cd8be76f9a7e967a13ab16193564cb402fc495c69366f5c58"
    },
    {
      "id": "span-live-eesi-org-43f4436b46",
      "locator": {
        "coordinateSpace": "text-offset",
        "lineEnd": 1,
        "lineStart": 1,
        "quote": "Data Center Power Demands Are Contributing to Higher Energy Bills | Article | EESI Advancing science-based solutions for a sustainable, resilient, and equitable world Top-Rated Climate Nonprofit – 4-Star Charity About About About Us Accompl",
        "quoteDigest": "sha256:b8ab05160ed96f550b0f9d37a7d7c0dce50a5f30002a7898e32911e57f3b90a6",
        "version": "1.0.0"
      },
      "parsedArtifactDigest": "sha256:1d332b12d666e2635170ecc4d47135705922fbaafd5ac388d395f6dc4eef537c",
      "parserId": "p8-live-text-parser",
      "parserVersion": "1.0.0",
      "rawSnapshotDigest": "sha256:43f4436b469d8198f66fd5138e56e6c1915328cceb09602f9d5934184c563ec9",
      "sourceId": "live-eesi-org-43f4436b46",
      "spanDigest": "sha256:2919c67cfc1885073c30d60316ad54dc427a703ad5d845296aa45e6e3d27b28e"
    },
    {
      "id": "span-live-eesi-org-bec8ea01d4",
      "locator": {
        "coordinateSpace": "text-offset",
        "lineEnd": 1,
        "lineStart": 1,
        "quote": "Data Centers and Water Consumption | Article | EESI Advancing science-based solutions for a sustainable, resilient, and equitable world Top-Rated Climate Nonprofit – 4-Star Charity About About About Us Accomplishments Advisory Board Careers",
        "quoteDigest": "sha256:5d9b223939131b6aa7e6bbccef01ebef18357703f9eef0aab7fb3ffb09dabff4",
        "version": "1.0.0"
      },
      "parsedArtifactDigest": "sha256:8115b0c3124a26b48c1dee05ac6c0953d8c26326a01bf4800c3bbb39bf552e41",
      "parserId": "p8-live-text-parser",
      "parserVersion": "1.0.0",
      "rawSnapshotDigest": "sha256:bec8ea01d479e9c8b70c3eef63e5df6bc19948bfdaafec809fa9bb7a7f42dac0",
      "sourceId": "live-eesi-org-bec8ea01d4",
      "spanDigest": "sha256:d2964e49c535fd5379b756b4ce49a27d1da033638f3cdade0deb82c890e23ab1"
    },
    {
      "id": "span-live-uga-edu-69cc36a64d",
      "locator": {
        "coordinateSpace": "text-offset",
        "lineEnd": 1,
        "lineStart": 1,
        "quote": "Understanding How Data Centers Impact Surface and Ground Waters | CAES Field Report Field Report Search for: Menu Search Search Stories ➤ Science in service of humanity and the environment Read our annual magazine here READ Dive into engagi",
        "quoteDigest": "sha256:306fb1626f878f3393f3243f99221214d259a5d345b51d98e49ba899e1a745e3",
        "version": "1.0.0"
      },
      "parsedArtifactDigest": "sha256:71b8370f3c45173574d25bdf165d44a506bb80ea9ff7109a0a1fb70b371d88af",
      "parserId": "p8-live-text-parser",
      "parserVersion": "1.0.0",
      "rawSnapshotDigest": "sha256:69cc36a64da3b92d9305e1d9321c969053a8e0dcece92dd4d1607f7e10e6926e",
      "sourceId": "live-uga-edu-69cc36a64d",
      "spanDigest": "sha256:ede708867f155fb4c41904042c82142358773f2c28d449d27aad2b47e758147c"
    },
    {
      "id": "span-live-akcp-com-0b184c7d39",
      "locator": {
        "coordinateSpace": "text-offset",
        "lineEnd": 1,
        "lineStart": 1,
        "quote": "Data Center Water Use and Its Environmental Impact Skip to content Platforms sensorProbe+ Series sensorProbe1+ sensorProbe2+ sensorProbe2+LCD sensorProbeX+ securityProbe Series securityProbe5E securityProbe 5E-X20 securityProbe 5E-X60 secur",
        "quoteDigest": "sha256:11a434f8ca063167e7109381dde75ffa06fb02ea79bccf68230434662f1eaa72",
        "version": "1.0.0"
      },
      "parsedArtifactDigest": "sha256:f3e218e74b2e7b1377d6af29656d2ee35c3ba5912866ec186189b846c0ef2725",
      "parserId": "p8-live-text-parser",
      "parserVersion": "1.0.0",
      "rawSnapshotDigest": "sha256:0b184c7d39cf2de525096494d4869a18566caeee056ce8ba740f2c86136a60e8",
      "sourceId": "live-akcp-com-0b184c7d39",
      "spanDigest": "sha256:71ee2df5d6c6aae877256868532acabe54406c20537ace3f9c56c4a980dc6f5b"
    },
    {
      "id": "span-live-fwpcoa-org-f5c5166a38",
      "locator": {
        "coordinateSpace": "text-offset",
        "lineEnd": 1,
        "lineStart": 1,
        "quote": "Myths vs. Reality: Data Centers And Water Usage - Florida Water and Pollution Control Operators Association Skip to main content &#xE314;  Print This Page &#xE262; Text Size &#xE55D; Scroll To Top Member Login Florida Water & Pollution Con",
        "quoteDigest": "sha256:dec9e6697dbe2cb2745a6cf3c98cf22392ac10e11857b79ed8507ec7d87a6d64",
        "version": "1.0.0"
      },
      "parsedArtifactDigest": "sha256:988b365d2a5bed969ea2463091504ad77b4dd122a2baeac42247685b539798ba",
      "parserId": "p8-live-text-parser",
      "parserVersion": "1.0.0",
      "rawSnapshotDigest": "sha256:f5c5166a38971ff1bc48e22f814c37a573b3d3efc0aeeb57ca9a8724f36a6d40",
      "sourceId": "live-fwpcoa-org-f5c5166a38",
      "spanDigest": "sha256:f207e9df34538096dd640328255f98ec980c8cec391a95109d054832fa54e9d2"
    },
    {
      "id": "span-live-nih-gov-050055ecca",
      "locator": {
        "coordinateSpace": "text-offset",
        "lineEnd": 1,
        "lineStart": 1,
        "quote": "Toward climate neutral data centers: Greenhouse gas inventory, scenarios, and strategies - PMC Skip to main content An official website of the United States government Here's how you know Here's how you know Official websites use .gov A .go",
        "quoteDigest": "sha256:5b86099a360fdcbfb38e9fabd67e48120242b8b3e6bba46bd65b087d91bb6920",
        "version": "1.0.0"
      },
      "parsedArtifactDigest": "sha256:004067790c10a14e2714439d88d2a18578df0d43bde2929bb9d197b144cf9256",
      "parserId": "p8-live-text-parser",
      "parserVersion": "1.0.0",
      "rawSnapshotDigest": "sha256:050055eccad0c493b5560a7a655a418543dcb8c0f98992676c0562b59b04e6f5",
      "sourceId": "live-nih-gov-050055ecca",
      "spanDigest": "sha256:de6ca1a6e292bb36617fb47151859653c1dc9ac784f276f99d877f12d3e319be"
    },
    {
      "id": "span-live-msci-com-e9b400d8d6",
      "locator": {
        "coordinateSpace": "text-offset",
        "lineEnd": 1,
        "lineStart": 1,
        "quote": "Desire for Data Centers Creates Carbon Dilemma for Property Investors | MSCI Global Client Support Client Log In Featured Solutions Featured solutions bring together a variety of products to create approaches customized to your needs Rules-",
        "quoteDigest": "sha256:7b641ee1e5a01a48b201e51f57ffbf52e38037ee2d7765e577d89fbffca21c15",
        "version": "1.0.0"
      },
      "parsedArtifactDigest": "sha256:e4bc0f343235745629ec7e29f267e745c8521e124c54269a2c48417772097cfb",
      "parserId": "p8-live-text-parser",
      "parserVersion": "1.0.0",
      "rawSnapshotDigest": "sha256:e9b400d8d621e2d9b9e4ee9c0eb4d21bce336e36a8b2c670e04d15c0cb3b7e71",
      "sourceId": "live-msci-com-e9b400d8d6",
      "spanDigest": "sha256:dd1ac64cec1268380591bc5e2ed0485c2062099385ffc9dceaffa8f4164b4c15"
    },
    {
      "id": "span-live-weforum-org-efbbb5c6a1",
      "locator": {
        "coordinateSpace": "text-offset",
        "lineEnd": 1,
        "lineStart": 1,
        "quote": "6 ways data centres can cut their emissions: A case study | World Economic Forum Emerging Technologies 6 ways data centres can cut their emissions — without compromising the AI boom Jan 16, 2025 Data centre electricity usage is expected to",
        "quoteDigest": "sha256:304379a9e9d564b7901c0bb60326133af5a7aabbcd84d286b4771f96a19d9e23",
        "version": "1.0.0"
      },
      "parsedArtifactDigest": "sha256:cbd6d0c3394276732b46cbe1d2a5e22048a860218a5af4f00b432a04ff3d13e2",
      "parserId": "p8-live-text-parser",
      "parserVersion": "1.0.0",
      "rawSnapshotDigest": "sha256:efbbb5c6a1cf3366fb06c499e84e70d6dbf5c591188bc8f2f37cabba26dd3f53",
      "sourceId": "live-weforum-org-efbbb5c6a1",
      "spanDigest": "sha256:deda86dceb7802101120a6aceabc19c4ba6956576a6f5b7923334ebe48ac6a00"
    },
    {
      "id": "span-live-eesi-org-0d574d148f",
      "locator": {
        "coordinateSpace": "text-offset",
        "lineEnd": 1,
        "lineStart": 1,
        "quote": "Communities Are Raising Noise Pollution Concerns About Data Centers | Article | EESI Advancing science-based solutions for a sustainable, resilient, and equitable world Top-Rated Climate Nonprofit – 4-Star Charity About About About Us Accom",
        "quoteDigest": "sha256:53ab9bc9b0d1b351ccb1b8627cd4fa1cd8aac517fca1c553aa8ec07d559db505",
        "version": "1.0.0"
      },
      "parsedArtifactDigest": "sha256:2dbf11b80071e18689699e4b648ecbd8bfe2d7973378609d746107ec5cfabff3",
      "parserId": "p8-live-text-parser",
      "parserVersion": "1.0.0",
      "rawSnapshotDigest": "sha256:0d574d148f82de5346ecc75bdf0ed2a58db4c9c80a3a3d34143164858e5d1169",
      "sourceId": "live-eesi-org-0d574d148f",
      "spanDigest": "sha256:636a9e762253af45cdf3bbc5b1c01357e2686ef3a18543d89e31cd473d24a985"
    },
    {
      "id": "span-live-usnews-com-13a2d7bacd",
      "locator": {
        "coordinateSpace": "text-offset",
        "lineEnd": 1,
        "lineStart": 1,
        "quote": "&#x27;Living in Hell&#x27;: Data Center Neighbors Grapple With Noise, Air Pollution | National News | U.S. News Skip to content News News Sections U.S. News Decision Points Capitol Chats Elections Top Stories Health News Politics World Repo",
        "quoteDigest": "sha256:f8634de1b63253bc1d7d6644abd9994914459164f51ca0c0537e6681f7e98187",
        "version": "1.0.0"
      },
      "parsedArtifactDigest": "sha256:055e268618f866b9983fc5cffbf0c4f85488bccfc7a0b3194d8ea10d23aac26b",
      "parserId": "p8-live-text-parser",
      "parserVersion": "1.0.0",
      "rawSnapshotDigest": "sha256:13a2d7bacd07ab1e81821ca3606f8ced8453f4b52b2ecf4ae7a1eda5fb591d3f",
      "sourceId": "live-usnews-com-13a2d7bacd",
      "spanDigest": "sha256:1184894a34f3296bfd8938d3c5bedb746a44fe9fb663d69d95b0bbce15c721f7"
    },
    {
      "id": "span-live-environmentalhealthproject-org-636b97f437",
      "locator": {
        "coordinateSpace": "text-offset",
        "lineEnd": 1,
        "lineStart": 1,
        "quote": "--> The Dangers of Data Centers top of page About Us Our Team Board Funders 10th Anniversary Careers Our Work Data Collection & Analysis Health & Wellness Education Policy & Advocacy Initiatives Annual Reports Sustainable Development Book C",
        "quoteDigest": "sha256:efa147909a13a790be537d5cd6307a69f3e99e432ff3621417aa6c417c9cbe87",
        "version": "1.0.0"
      },
      "parsedArtifactDigest": "sha256:6e73f680ad8ce75a9d97ecd805e102e46e0877777b4944469f94d62d8b03ec10",
      "parserId": "p8-live-text-parser",
      "parserVersion": "1.0.0",
      "rawSnapshotDigest": "sha256:636b97f4375b3d7db82d2a1ab1a16200dcfa0a81c2b771afc17bce1e66e7beed",
      "sourceId": "live-environmentalhealthproject-org-636b97f437",
      "spanDigest": "sha256:c95bc951219ce356b421d07bd6de7deded9bf77ea8d4f89b6df8af96cc01a61b"
    },
    {
      "id": "span-live-theconversation-com-8a81b0f41b",
      "locator": {
        "coordinateSpace": "text-offset",
        "lineEnd": 1,
        "lineStart": 1,
        "quote": "5 ways data centers endanger their local communities and the country as a whole Search analysis, research, academics… Home Podcasts Arts Business + Economy Culture + Society Education Environment + Energy Health Politics Science + Tech En f",
        "quoteDigest": "sha256:18d625538f08c38689ff47be7df75a9ffb569332a6a1f8bb8ebfe49f36d868e3",
        "version": "1.0.0"
      },
      "parsedArtifactDigest": "sha256:22508c6e64ca13b4eefbc0e39da347dd20aea0fd9d981d34f19008b8d9fc5728",
      "parserId": "p8-live-text-parser",
      "parserVersion": "1.0.0",
      "rawSnapshotDigest": "sha256:8a81b0f41b99836fe035039f337e48b8403fb760c3670a49172125184d554c63",
      "sourceId": "live-theconversation-com-8a81b0f41b",
      "spanDigest": "sha256:793f64f6b577d77798fc43bffb14ce3056a0e1c533bb6719fd49864aedc9e53f"
    },
    {
      "id": "span-live-wri-org-d2560ad4e3",
      "locator": {
        "coordinateSpace": "text-offset",
        "lineEnd": 1,
        "lineStart": 1,
        "quote": "7 Ways Data Centers Affect US Communities | World Resources Institute Skip to main content Accessibility World Resources Institute Making Big Ideas Happen Main navigation Research Data Initiatives Insights Most Recent Podcasts News All Insi",
        "quoteDigest": "sha256:af5dfa55d9a020ba236b53f75522700ed7904fdba3bf4cebdafde9cc5e61c9a6",
        "version": "1.0.0"
      },
      "parsedArtifactDigest": "sha256:c287685c05cbf6b6156ce2dc6681d773ce28a7c7ac345dbbc440db6edec1913c",
      "parserId": "p8-live-text-parser",
      "parserVersion": "1.0.0",
      "rawSnapshotDigest": "sha256:d2560ad4e361ddb71a8a3f0b1922ab8d426d2b2fa3e232f5aa6e95b5eb3adb19",
      "sourceId": "live-wri-org-d2560ad4e3",
      "spanDigest": "sha256:9c3f88a4711aca2e87130b4b96ded6bf469df2ebac292088f9d3078fd34bbabf"
    },
    {
      "id": "span-live-datacentercoalition-org-46a7b53f32",
      "locator": {
        "coordinateSpace": "text-offset",
        "lineEnd": 1,
        "lineStart": 1,
        "quote": "Data Center FAQs Skip to Main Content This site uses cookies to provide you with a great user experience. By continuing to use our site, we shall assume that you accept our use of cookies. I Understand Join Now Login About Us Members Board",
        "quoteDigest": "sha256:595935e2342304198f8390cd476630cecf45ed1d39b49dc46b9d8def5478d3c6",
        "version": "1.0.0"
      },
      "parsedArtifactDigest": "sha256:0b098a9ea6f4f7629830b4ec5717e589153562a88a6e02f7f0d81acc5c55a428",
      "parserId": "p8-live-text-parser",
      "parserVersion": "1.0.0",
      "rawSnapshotDigest": "sha256:46a7b53f3296ae3040b3168ce9683ef2e0182e31844799feb441880268f8d110",
      "sourceId": "live-datacentercoalition-org-46a7b53f32",
      "spanDigest": "sha256:5cb55f07217feaff61376d7086aa8f0b6ad242bb35995f0e271a0545adcedb00"
    }
  ],
  "generatedAt": "2026-07-14T20:34:04.475Z",
  "manifestDigest": "sha256:427c5e9e10bb98e1ad6af41b00fedf2a13ca62900dbed8b1e9509f9275f95b57",
  "mode": "report",
  "question": "What impacts do data centers have on the communities and environment around them?",
  "schemaVersion": "1.0.0"
}
